practica-15/inciso-b/inciso_b.vhdl
library IEEE;
use IEEE.std_logic_1164.all;
use IEEE.numeric_std.all;

entity inciso_b is
  port (
    bcd: in std_logic_vector(3 downto 0);
    display: out std_logic_vector(6 downto 0)
  );
end entity inciso_b;

architecture a_inciso_b of inciso_b is
begin
  process(bcd)
  begin
    if (bcd = "0000") then
      display <= "0000001";
    elsif (bcd = "0001") then
      display <= "1001111";
    elsif (bcd = "0010") then
      display <= "0010010";
    elsif (bcd = "0011") then
      display <= "0000110";
    elsif (bcd = "0100") then
      display <= "1001100";
    elsif (bcd = "0101") then
      display <= "0100100";
    elsif (bcd = "0110") then
      display <= "0001111";
    elsif (bcd = "0111") then
      display <= "0001111";
    elsif (bcd = "1000") then
      display <= "0000000";
    elsif (bcd = "1001") then
      display <= "0000100";
    else
      display <= "1111111";
    end if;
  end process;
end architecture a_inciso_b;

practica-15/inciso-b/inciso_b_tb.vhdl
library IEEE;
use IEEE.std_logic_1164.all;
use IEEE.numeric_std.all;

entity inciso_b_tb is
end inciso_b_tb;

architecture prueba_inciso_b of inciso_b_tb is
  component inciso_b
    port (
      bcd: in std_logic_vector(3 downto 0);
      display: out std_logic_vector(6 downto 0)
    );
  end component;

  signal bcd: std_logic_vector(3 downto 0);
  signal display: std_logic_vector(6 downto 0);
begin
  incisoB: inciso_b port map(bcd => bcd, display => display);
  
  process begin
    bcd <= "0000";
    wait for 1 ns;
    assert (display = "0000001") report "Error en 0";
    
    bcd <= "0001";
    wait for 1 ns;
    assert (display = "1001111") report "Error en 1";

    bcd <= "0010";
    wait for 1 ns;
    assert (display = "0010010") report "Error en 2";

    bcd <= "0011";
    wait for 1 ns;
    assert (display = "0000110") report "Error en 3";

    bcd <= "0100";
    wait for 1 ns;
    assert (display = "1001100") report "Error en 4";

    bcd <= "0101";
    wait for 1 ns;
    assert (display = "0100100") report "Error en 5";

    bcd <= "0110";
    wait for 1 ns;
    assert (display = "0001111") report "Error en 6";

    bcd <= "0111";
    wait for 1 ns;
    assert (display = "0001111") report "Error en 7";

    bcd <= "1000";
    wait for 1 ns;
    assert (display = "0000000") report "Error en 8";

    bcd <= "1001";
    wait for 1 ns;
    assert (display = "0000100") report "Error en 9";

    bcd <= "1010";
    wait for 1 ns;
    assert (display = "1111111") report "Error en caso fuera de control";

    -- Mensaje para finalización de la simulación.
    assert false report "Fin de la prueba, sin errores.";
    wait;
  end process;
end architecture prueba_inciso_b;

practica-15/inciso-b/inciso_b.vcd
$date
  Sun May 30 04:59:33 2021
$end
$version
  GHDL v0
$end
$timescale
  1 fs
$end
$scope module standard $end
$upscope $end
$scope module std_logic_1164 $end
$upscope $end
$scope module numeric_std $end
$upscope $end
$scope module inciso_b_tb $end
$var reg 4 ! bcd[3:0] $end
$var reg 7 " display[6:0] $end
$scope module incisob $end
$var reg 4 # bcd[3:0] $end
$var reg 7 $ display[6:0] $end
$upscope $end
$upscope $end
$enddefinitions $end
#0
b0000 !
b0000001 "
b0000 #
b0000001 $
#1000000
b0001 !
b1001111 "
b0001 #
b1001111 $
#2000000
b0010 !
b0010010 "
b0010 #
b0010010 $
#3000000
b0011 !
b0000110 "
b0011 #
b0000110 $
#4000000
b0100 !
b1001100 "
b0100 #
b1001100 $
#5000000
b0101 !
b0100100 "
b0101 #
b0100100 $
#6000000
b0110 !
b0001111 "
b0110 #
b0001111 $
#7000000
b0111 !
b0111 #
#8000000
b1000 !
b0000000 "
b1000 #
b0000000 $
#9000000
b1001 !
b0000100 "
b1001 #
b0000100 $
#10000000
b1010 !
b1111111 "
b1010 #
b1111111 $
