practica-15/inciso-c/inciso_c.vhdl
library IEEE;
use IEEE.std_logic_1164.all;
use IEEE.numeric_std.all;

entity inciso_c is
  port (
    bcd: in std_logic_vector(3 downto 0);
    display: out std_logic_vector(6 downto 0)
  );
end entity inciso_c;

architecture a_inciso_c of inciso_c is
begin
process(bcd)
begin
  case bcd is
    when "0000" =>
      display <= "1111110";
    when "0001" =>
      display <= "0110000";
    when "0010" =>
      display <= "1101101";
    when "0011" =>
      display <= "1111001";
    when "0100" =>
      display <= "0110011";
    when "0101" =>
      display <= "1011011";
    when "0110" =>
      display <= "1110000";
    when "0111" =>
      display <= "1110000";
    when "1000" =>
      display <= "1111111";
    when "1001" =>
      display <= "1111011";
    when "1010" =>
      display <= "1110111";
    when "1011" =>
      display <= "0011111";
    when "1100" =>
      display <= "1001110";
    when "1101" =>
      display <= "0111101";
    when "1110" =>
      display <= "1001111";
    when "1111" =>
      display <= "1000111";
    when others =>
      display <= "0000000";
  end case;
end process;
end architecture a_inciso_c;

practica-15/inciso-c/inciso_c_tb.vhdl
library IEEE;
use IEEE.std_logic_1164.all;
use IEEE.numeric_std.all;

entity inciso_c_tb is
end entity inciso_c_tb;

architecture prueba_inciso_c of inciso_c_tb is
  component inciso_c
    port (
    bcd: in std_logic_vector(3 downto 0);
    display: out std_logic_vector(6 downto 0)
  );
  end component inciso_c;

  signal bcd: std_logic_vector(3 downto 0);
  signal display: std_logic_vector(6 downto 0);
begin
  incisoC: inciso_c port map(bcd => bcd, display => display);

  -- Comienzan las pruebas.
  process begin
    bcd <= "0000";
    wait for 1 ns;

    bcd <= "0001";
    wait for 1 ns;

    bcd <= "0010";
    wait for 1 ns;

    bcd <= "0011";
    wait for 1 ns;

    bcd <= "0100";
    wait for 1 ns;

    bcd <= "0101";
    wait for 1 ns;

    bcd <= "0110";
    wait for 1 ns;

    bcd <= "0111";
    wait for 1 ns;

    bcd <= "1000";
    wait for 1 ns;

    bcd <= "1001";
    wait for 1 ns;

    bcd <= "1010";
    wait for 1 ns;

    bcd <= "1011";
    wait for 1 ns;

    bcd <= "1100";
    wait for 1 ns;

    bcd <= "1101";
    wait for 1 ns;

    bcd <= "1110";
    wait for 1 ns;

    bcd <= "1111";
    wait for 1 ns;

    assert false report "Fin de prueba";
    wait;
  end process;
  
end architecture prueba_inciso_c;

practica-15/inciso-c/inciso_c.vcd
$date
  Sun May 30 16:33:08 2021
$end
$version
  GHDL v0
$end
$timescale
  1 fs
$end
$scope module standard $end
$upscope $end
$scope module std_logic_1164 $end
$upscope $end
$scope module numeric_std $end
$upscope $end
$scope module inciso_c_tb $end
$var reg 4 ! bcd[3:0] $end
$var reg 7 " display[6:0] $end
$scope module incisoc $end
$var reg 4 # bcd[3:0] $end
$var reg 7 $ display[6:0] $end
$upscope $end
$upscope $end
$enddefinitions $end
#0
b0000 !
b1111110 "
b0000 #
b1111110 $
#1000000
b0001 !
b0110000 "
b0001 #
b0110000 $
#2000000
b0010 !
b1101101 "
b0010 #
b1101101 $
#3000000
b0011 !
b1111001 "
b0011 #
b1111001 $
#4000000
b0100 !
b0110011 "
b0100 #
b0110011 $
#5000000
b0101 !
b1011011 "
b0101 #
b1011011 $
#6000000
b0110 !
b1110000 "
b0110 #
b1110000 $
#7000000
b0111 !
b0111 #
#8000000
b1000 !
b1111111 "
b1000 #
b1111111 $
#9000000
b1001 !
b1111011 "
b1001 #
b1111011 $
#10000000
b1010 !
b1110111 "
b1010 #
b1110111 $
#11000000
b1011 !
b0011111 "
b1011 #
b0011111 $
#12000000
b1100 !
b1001110 "
b1100 #
b1001110 $
#13000000
b1101 !
b0111101 "
b1101 #
b0111101 $
#14000000
b1110 !
b1001111 "
b1110 #
b1001111 $
#15000000
b1111 !
b1000111 "
b1111 #
b1000111 $
