practica-15/inciso-a/inciso-a.vhdl
library IEEE;
use IEEE.std_logic_1164.all;
use IEEE.numeric_std.all;

entity incisoA is
  port (
    bcd: in std_logic_vector(3 downto 0);
    display: out std_logic_vector(6 downto 0)
  );
end entity incisoA;

architecture AIncisoA of incisoA is
begin
process(bcd)
begin
  case bcd is
    when "0000" =>
      display <= "1111110";
    when "0001" =>
      display <= "0110000";
    when "0010" =>
      display <= "1101101";
    when "0011" =>
      display <= "1111001";
    when "0100" =>
      display <= "0110011";
    when "0101" =>
      display <= "1011011";
    when "0110" =>
      display <= "1110000";
    when "0111" =>
      display <= "1110000";
    when "1000" =>
      display <= "1111111";
    when "1001" =>
      display <= "1111011";
    when others =>
      display <= "0000000";
  end case;
end process;
end architecture AIncisoA;

practica-15/inciso-a/inciso-a-tb.vhdl
library IEEE;
use IEEE.std_logic_1164.all;
use IEEE.numeric_std.all;

entity incisoA_tb is
end incisoA_tb;

architecture prueba of incisoA_tb is
  component incisoA
    port (
      bcd: in std_logic_vector(3 downto 0);
      display: out std_logic_vector(6 downto 0)
    );
  end component;

  signal bcd: std_logic_vector(3 downto 0);
  signal display: std_logic_vector(6 downto 0);
begin
  inciso_a: incisoA port map(bcd => bcd, display => display);
  
  process begin
    bcd <= "0000";
    wait for 1 ns;
    assert (display = "1111110") report "Error en 0";
    
    bcd <= "0001";
    wait for 1 ns;
    assert (display = "0110000") report "Error en 1";

    bcd <= "0010";
    wait for 1 ns;
    assert (display = "1101101") report "Error en 2";

    bcd <= "0011";
    wait for 1 ns;
    assert (display = "1111001") report "Error en 3";

    bcd <= "0100";
    wait for 1 ns;
    assert (display = "0110011") report "Error en 4";

    bcd <= "0101";
    wait for 1 ns;
    assert (display = "1011011") report "Error en 5";

    bcd <= "0110";
    wait for 1 ns;
    assert (display = "1110000") report "Error en 6";

    bcd <= "0111";
    wait for 1 ns;
    assert (display = "1110000") report "Error en 7";

    bcd <= "1000";
    wait for 1 ns;
    assert (display = "1111111") report "Error en 8";

    bcd <= "1001";
    wait for 1 ns;
    assert (display = "1111011") report "Error en 9";

    bcd <= "1010";
    wait for 1 ns;
    assert (display = "0000000") report "Error en caso fuera de control";

    -- Mensaje para finalización de la simulación.
    assert false report "Fin de la prueba, sin errores.";
    wait;
  end process;
end architecture prueba;

practica-15/inciso-a/incisoa.vcd
$date
  Sun May 30 01:23:35 2021
$end
$version
  GHDL v0
$end
$timescale
  1 fs
$end
$scope module standard $end
$upscope $end
$scope module std_logic_1164 $end
$upscope $end
$scope module numeric_std $end
$upscope $end
$scope module incisoa_tb $end
$var reg 4 ! bcd[3:0] $end
$var reg 7 " display[6:0] $end
$scope module inciso_a $end
$var reg 4 # bcd[3:0] $end
$var reg 7 $ display[6:0] $end
$upscope $end
$upscope $end
$enddefinitions $end
#0
b0000 !
b1111110 "
b0000 #
b1111110 $
#1000000
b0001 !
b0110000 "
b0001 #
b0110000 $
#2000000
b0010 !
b1101101 "
b0010 #
b1101101 $
#3000000
b0011 !
b1111001 "
b0011 #
b1111001 $
#4000000
b0100 !
b0110011 "
b0100 #
b0110011 $
#5000000
b0101 !
b1011011 "
b0101 #
b1011011 $
#6000000
b0110 !
b1110000 "
b0110 #
b1110000 $
#7000000
b0111 !
b0111 #
#8000000
b1000 !
b1111111 "
b1000 #
b1111111 $
#9000000
b1001 !
b1111011 "
b1001 #
b1111011 $
#10000000
b1010 !
b0000000 "
b1010 #
b0000000 $
